{
  "projectRoot": "/Users/riaverma/github_repos/coffee_app",
  "batchFiles": [
    {"path": ".cursor/plans/coffee_app_frontend_&_backend_integration_acbf5cbd.plan.md", "language": "markdown", "sizeLines": 0, "fileCategory": "docs"},
    {"path": ".cursor/plans/json_to_supabase_migration_cf766576.plan.md", "language": "markdown", "sizeLines": 0, "fileCategory": "docs"},
    {"path": ".cursor/plans/migrate_to_vercel_+_railway_9ead5567.plan.md", "language": "markdown", "sizeLines": 0, "fileCategory": "docs"},
    {"path": ".cursor/plans/places_bootstrap_enrichment_system_16b8e353.plan.md", "language": "markdown", "sizeLines": 0, "fileCategory": "docs"},
    {"path": ".cursor/plans/restructure_enrichment_for_latency_and_cost_reduction_4d1a6478.plan.md", "language": "markdown", "sizeLines": 0, "fileCategory": "docs"},
    {"path": ".env.example", "language": "config", "sizeLines": 41, "fileCategory": "config"},
    {"path": ".env.local", "language": "config", "sizeLines": 5, "fileCategory": "config"},
    {"path": "DEPLOYMENT.md", "language": "markdown", "sizeLines": 270, "fileCategory": "docs"},
    {"path": "README.md", "language": "markdown", "sizeLines": 246, "fileCategory": "docs"},
    {"path": "backend/.env.local", "language": "config", "sizeLines": 15, "fileCategory": "config"},
    {"path": "backend/requirements.txt", "language": "text", "sizeLines": 9, "fileCategory": "docs"},
    {"path": "render.yaml", "language": "yaml", "sizeLines": 18, "fileCategory": "config"},
    {"path": "coffee-map/README.md", "language": "markdown", "sizeLines": 36, "fileCategory": "docs"},
    {"path": "docs/v2-architecture-plan.md", "language": "markdown", "sizeLines": 794, "fileCategory": "docs"},
    {"path": "docs/v2-sequence-diagram.md", "language": "markdown", "sizeLines": 109, "fileCategory": "docs"},
    {"path": "coffee-map/package.json", "language": "json", "sizeLines": 27, "fileCategory": "config"},
    {"path": "coffee-map/tsconfig.json", "language": "json", "sizeLines": 34, "fileCategory": "config"},
    {"path": "backend/supabase/schema.sql", "language": "sql", "sizeLines": 248, "fileCategory": "data"},
    {"path": "backend/supabase/seed.sql", "language": "sql", "sizeLines": 9, "fileCategory": "data"},
    {"path": "docs/supabase_schema_docs/migrations/001_create_tables.sql", "language": "sql", "sizeLines": 86, "fileCategory": "data"},
    {"path": "docs/supabase_schema_docs/migrations/002_create_indexes.sql", "language": "sql", "sizeLines": 24, "fileCategory": "data"},
    {"path": "docs/supabase_schema_docs/migrations/003_create_triggers.sql", "language": "sql", "sizeLines": 76, "fileCategory": "data"},
    {"path": "docs/supabase_schema_docs/migrations/004_multi_mention.sql", "language": "sql", "sizeLines": 44, "fileCategory": "data"},
    {"path": "docs/supabase_schema_docs/seed/nyc_regions.sql", "language": "sql", "sizeLines": 17, "fileCategory": "data"},
    {"path": "coffee-map/app/globals.css", "language": "css", "sizeLines": 26, "fileCategory": "markup"},
    {"path": "coffee-map/eslint.config.mjs", "language": "javascript", "sizeLines": 18, "fileCategory": "code"},
    {"path": "coffee-map/postcss.config.mjs", "language": "javascript", "sizeLines": 7, "fileCategory": "code"},
    {"path": "coffee-map/next.config.ts", "language": "typescript", "sizeLines": 8, "fileCategory": "code"}
  ],
  "batchImportData": {
    ".cursor/plans/coffee_app_frontend_&_backend_integration_acbf5cbd.plan.md": [],
    ".cursor/plans/json_to_supabase_migration_cf766576.plan.md": [],
    ".cursor/plans/migrate_to_vercel_+_railway_9ead5567.plan.md": [],
    ".cursor/plans/places_bootstrap_enrichment_system_16b8e353.plan.md": [],
    ".cursor/plans/restructure_enrichment_for_latency_and_cost_reduction_4d1a6478.plan.md": [],
    ".env.example": [],
    ".env.local": [],
    "DEPLOYMENT.md": [],
    "README.md": [],
    "backend/.env.local": [],
    "backend/requirements.txt": [],
    "render.yaml": [],
    "coffee-map/README.md": [],
    "docs/v2-architecture-plan.md": [],
    "docs/v2-sequence-diagram.md": [],
    "coffee-map/package.json": [],
    "coffee-map/tsconfig.json": [],
    "backend/supabase/schema.sql": [],
    "backend/supabase/seed.sql": [],
    "docs/supabase_schema_docs/migrations/001_create_tables.sql": [],
    "docs/supabase_schema_docs/migrations/002_create_indexes.sql": [],
    "docs/supabase_schema_docs/migrations/003_create_triggers.sql": [],
    "docs/supabase_schema_docs/migrations/004_multi_mention.sql": [],
    "docs/supabase_schema_docs/seed/nyc_regions.sql": [],
    "coffee-map/app/globals.css": [],
    "coffee-map/eslint.config.mjs": [],
    "coffee-map/postcss.config.mjs": [],
    "coffee-map/next.config.ts": []
  }
}
